setup.py
wishbone_input_hammer/__init__.py
wishbone_input_hammer/hammer.py
wishbone_input_hammer.egg-info/PKG-INFO
wishbone_input_hammer.egg-info/SOURCES.txt
wishbone_input_hammer.egg-info/dependency_links.txt
wishbone_input_hammer.egg-info/entry_points.txt
wishbone_input_hammer.egg-info/namespace_packages.txt
wishbone_input_hammer.egg-info/not-zip-safe
wishbone_input_hammer.egg-info/requires.txt
wishbone_input_hammer.egg-info/top_level.txt